{
  "categories": [
    {
      "name": "Home",
      "icon": "control_home.png",
      "subcategories": [],
      "append_divider": "true"
    },
    {
      "name": "Erdgeschoss",
      "icon": "control_building_modern_s_okg_eg.png",
      "subcategories": ["Badezimmer", "Esszimmer", "Küche", "Wohnzimmer"]
    },
    {
      "name": "Obergeschoss",
      "icon": "control_building_modern_s_okg_og.png",
      "subcategories": ["Büro", "Schlafzimmer", "Toilette"]
    },
    {
      "name": "Dachgeschoss",
      "icon": "control_building_modern_s_okg_dg.png",
      "subcategories": ["Kinderzimmer"]
    },
    {
      "name": "Einfahrt",
      "icon": "fts_garage.png",
      "subcategories": []
    },
    {
      "name": "Garten",
      "icon": "scene_garden.png",
      "subcategories": [],
      "append_divider": "true"
    },
    {
      "name": "Aktoren",
      "icon": "message_socket_on_off.png",
      "subcategories": []
    },
    {
      "name": "CUxD",
      "icon": "time_timer.png",
      "subcategories": []
    },
    {
      "name": "Custom",
      "icon": "scene_making_love_clean.png",
      "subcategories": []
    },
    {
      "name": "Fenster",
      "icon": "fts_window_2w_open_l.png",
      "subcategories": []
    },
    {
      "name": "Heizung",
      "icon": "sani_heating.png",
      "subcategories": []
    },
    {
      "name": "Sender",
      "icon": "control_switch_m_4.png",
      "subcategories": []
    },
    {
      "name": "Sicherheit",
      "icon": "secur_alarm_alarm.png",
      "subcategories": []
    },
    {
      "name": "Wetter",
      "icon": "temp_temperature.png",
      "subcategories": []
    },
    {
      "name": "Programme",
      "icon": "audio_play.png",
      "subcategories": []
    },
    {
      "name": "Systemvariablen",
      "icon": "control_clear.png",
      "subcategories": [],
      "append_divider": "true"
    },
    {
      "name": "Import",
      "icon": "edit_settings.png",
      "subcategories": []
    }
  ]
}